db_hooks_manager24/__init__.py
db_hooks_manager24/core.py
db_hooks_manager24-0.1.3.dist-info/METADATA
db_hooks_manager24-0.1.3.dist-info/WHEEL
db_hooks_manager24-0.1.3.dist-info/RECORD
